vcham/__init__.py
vcham/constants.py
vcham/couplingfunct.py
vcham/diabfunct.py
vcham/gui.py
vcham/logging_config.py
vcham/lvc.py
vcham/symm_vcham.py
vcham/utils.py
vcham/vcham_system.py
vcham-0.0.4.dist-info/METADATA
vcham-0.0.4.dist-info/WHEEL
vcham-0.0.4.dist-info/licenses/LICENSE.md
vcham-0.0.4.dist-info/RECORD
