Metadata-Version: 2.4
Name: vcham
Version: 0.0.4
Summary: A Vibronic Coupling Hamiltonian Tool
Project-URL: Gitlab, https://gitlab.com/tc-heidelberg/pyvcham
Author-email: Emilio Rodríguez Cuenca <emilioerc@gmail.com>
License: Copyright 2025, Emilio Rodríguez Cuenca.
License-File: LICENSE.md
Keywords: Hamiltonian,MCTHD,coupling,diabatic,diabatization,vibronic
Classifier: License :: OSI Approved :: MIT License
Classifier: Operating System :: OS Independent
Classifier: Programming Language :: Python :: 3
Classifier: Programming Language :: Python :: 3.9
Classifier: Programming Language :: Python :: 3.10
Classifier: Programming Language :: Python :: 3.11
Classifier: Programming Language :: Python :: 3.12
Requires-Python: <3.13,>=3.9
Requires-Dist: matplotlib
Requires-Dist: numpy
Requires-Dist: sphinx
Requires-Dist: sphinx-rtd-theme
Requires-Dist: tensorflow>=2.17.0
